README.md
setup.cfg
setup.py
quarksmart/__init__.py
quarksmart/quarksmart.py
quarksmart/settings.py
quarksmart.egg-info/PKG-INFO
quarksmart.egg-info/SOURCES.txt
quarksmart.egg-info/dependency_links.txt
quarksmart.egg-info/top_level.txt