Metadata-Version: 1.0
Name: quarksmart
Version: 1.1.0
Summary: Biblioteca para integração entre o Python e o sistema QuarkSmart.
Home-page: UNKNOWN
Author: ESIG Software
Author-email: contato@esig.com.br
License: UNKNOWN
Keywords: data science quarksmart
Platform: UNKNOWN
